{
  "name": "t:sections.header.name",
  "type": "header",
  "sections": {
    "announcement-bar": {
      "type": "announcement-bar",
      "blocks": {
        "announcement-bar-0": {
          "type": "announcement",
          "settings": {
            "announcement_text": "Welcome to our store",
            "announcement_link": ""
          }
        },
        "5b53534e-7dba-491e-a713-c7b24913c829": {
          "type": "announcement",
          "settings": {
            "announcement_text": "Hello World",
            "announcement_link": ""
          }
        }
      },
      "block_order": [
        "announcement-bar-0",
        "5b53534e-7dba-491e-a713-c7b24913c829"
      ],
      "settings": {
      }
    },
    "header": {
      "type": "header",
      "settings": {
        "menu": "main-menu"
      }
    }
  },
  "order": [
    "announcement-bar",
    "header"
  ]
}
